{
  "project_info": {
    "project_number": "20844826489",
    "firebase_url": "https://mental1234-default-rtdb.firebaseio.com",
    "project_id": "mental1234",
    "storage_bucket": "mental1234.firebasestorage.app"
  },
  "client": [
    {
      "client_info": {
        "mobilesdk_app_id": "1:20844826489:android:8c26d0d87b4d91b79329a8",
        "android_client_info": {
          "package_name": "com.example.mental_health_care"
        }
      },
      "oauth_client": [
        {
          "client_id": "20844826489-suabt0t5i5lbcifd955aibefj0eq3ov9.apps.googleusercontent.com",
          "client_type": 3
        }
      ],
      "api_key": [
        {
          "current_key": "AIzaSyBXby4Os1y_X7KdT1X4HIm_BxRDN3x7S0g"
        }
      ],
      "services": {
        "appinvite_service": {
          "other_platform_oauth_client": [
            {
              "client_id": "20844826489-suabt0t5i5lbcifd955aibefj0eq3ov9.apps.googleusercontent.com",
              "client_type": 3
            },
            {
              "client_id": "20844826489-vbkhra29crd0b1dn6vicof3nn8qrp2dq.apps.googleusercontent.com",
              "client_type": 2,
              "ios_info": {
                "bundle_id": "com.example.mentalHealthCare"
              }
            }
          ]
        }
      }
    }
  ],
  "configuration_version": "1"
}